shrimp/__init__.py
shrimp/_parsers.py
shrimp/errors.py
shrimp/httpmethod.py
shrimp/httpstatus.py
shrimp/request.py
shrimp/response.py
shrimp/route.py
shrimp/shrimp.py
shrimp/_tools/maybe_coroutine.py
shrimp_http-0.1.4.dist-info/LICENSE
shrimp_http-0.1.4.dist-info/METADATA
shrimp_http-0.1.4.dist-info/WHEEL
shrimp_http-0.1.4.dist-info/top_level.txt
shrimp_http-0.1.4.dist-info/RECORD
