Metadata-Version: 2.1
Name: shrimp-http
Version: 0.1.4
Summary: Shrimp 🦐 is a batteries-included zero-dependency WSGI/ASGI web-framework for Python
Author: Krill Issue
License: MIT License
Project-URL: Homepage, https://github.com/krillissue/shrimp
Keywords: wsgi,asgi,server,webserver,api,web,framework
Classifier: License :: OSI Approved :: MIT License
Classifier: Programming Language :: Python
Classifier: Programming Language :: Python :: 3
Requires-Python: >=3.10
License-File: LICENSE
Provides-Extra: dev
Requires-Dist: black ; extra == 'dev'
